py_ai_toolkit/__init__.py
py_ai_toolkit/factories.py
py_ai_toolkit/adapters/__init__.py
py_ai_toolkit/adapters/instructor_adapter.py
py_ai_toolkit/adapters/jinja2_adapter.py
py_ai_toolkit/adapters/pydantic_adapter.py
py_ai_toolkit/core/base.py
py_ai_toolkit/core/tools.py
py_ai_toolkit/core/utils.py
py_ai_toolkit/core/domain/errors.py
py_ai_toolkit/core/domain/interfaces.py
py_ai_toolkit/core/domain/models.py
py_ai_toolkit/core/ports/__init__.py
py_ai_toolkit/core/ports/formatter_port.py
py_ai_toolkit/core/ports/llm_port.py
py_ai_toolkit/core/ports/modeller_port.py
py_ai_toolkit-0.5.1.dist-info/licenses/LICENSE.txt
py_ai_toolkit-0.5.1.dist-info/METADATA
py_ai_toolkit-0.5.1.dist-info/WHEEL
py_ai_toolkit-0.5.1.dist-info/top_level.txt
py_ai_toolkit-0.5.1.dist-info/RECORD
